roboflex/webcam_gst/__init__.py
roboflex/webcam_gst/roboflex_webcam_gst_ext.cpython-311-darwin.so
roboflex_webcam_gst-0.1.1.dist-info/licenses/LICENSE
roboflex_webcam_gst-0.1.1.dist-info/METADATA
roboflex_webcam_gst-0.1.1.dist-info/WHEEL
roboflex_webcam_gst-0.1.1.dist-info/top_level.txt
roboflex_webcam_gst-0.1.1.dist-info/RECORD
